photontorch/__init__.py
photontorch/components/__init__.py
photontorch/components/component.py
photontorch/components/connection.py
photontorch/components/directionalcouplers.py
photontorch/components/gratingcouplers.py
photontorch/components/mirrors.py
photontorch/components/mmis.py
photontorch/components/mzis.py
photontorch/components/soas.py
photontorch/components/terms.py
photontorch/components/waveguides.py
photontorch/detectors/__init__.py
photontorch/detectors/lowpassdetector.py
photontorch/detectors/photodetector.py
photontorch/environment/__init__.py
photontorch/environment/environment.py
photontorch/networks/__init__.py
photontorch/networks/clements.py
photontorch/networks/network.py
photontorch/networks/reck.py
photontorch/networks/rings.py
photontorch/networks/visualize.py
photontorch/nn/__init__.py
photontorch/nn/nn.py
photontorch-0.4.1.dist-info/LICENSE
photontorch-0.4.1.dist-info/METADATA
photontorch-0.4.1.dist-info/WHEEL
photontorch-0.4.1.dist-info/top_level.txt
photontorch-0.4.1.dist-info/RECORD
