Metadata-Version: 2.1
Name: photontorch
Version: 0.4.1
Summary: PhotonTorch: a photonic simulation framework based on the deep learning framework PyTorch.
Home-page: http://github.com/flaport/photontorch
Author: Floris Laporte
Author-email: floris.laporte@ugent.be
License: UNKNOWN
Platform: UNKNOWN
Classifier: Programming Language :: Python :: 3
Classifier: Programming Language :: Python :: 2.7
Classifier: Development Status :: 3 - Alpha
Classifier: Operating System :: OS Independent
Classifier: License :: OSI Approved :: GNU Affero General Public License v3
Classifier: Topic :: Scientific/Engineering
Classifier: Topic :: Scientific/Engineering :: Physics
Classifier: Topic :: Scientific/Engineering :: Artificial Intelligence
